jdProcessFileWatcher/Constants.py
jdProcessFileWatcher/Environment.py
jdProcessFileWatcher/FileAction.py
jdProcessFileWatcher/Functions.py
jdProcessFileWatcher/Icon.png
jdProcessFileWatcher/StraceWrapper.py
jdProcessFileWatcher/Types.py
jdProcessFileWatcher/Version.txt
jdProcessFileWatcher/__init__.py
jdProcessFileWatcher/core/Exporter.py
jdProcessFileWatcher/core/Filter.py
jdProcessFileWatcher/core/Languages.py
jdProcessFileWatcher/core/Settings.py
jdProcessFileWatcher/core/__init__.py
jdProcessFileWatcher/data/changelog.html
jdProcessFileWatcher/data/translators.json
jdProcessFileWatcher/dbus/jdProcessFileWatcherInterface.py
jdProcessFileWatcher/dbus/jdProcessFileWatcherInterface.xml
jdProcessFileWatcher/gui/AboutDialog.py
jdProcessFileWatcher/gui/ActionsTable.py
jdProcessFileWatcher/gui/ExportDialog.py
jdProcessFileWatcher/gui/FilterWidgets.py
jdProcessFileWatcher/gui/MainWindow.py
jdProcessFileWatcher/gui/PathActionsDialog.py
jdProcessFileWatcher/gui/RunCommandDialog.py
jdProcessFileWatcher/gui/RunProgramDialog.py
jdProcessFileWatcher/gui/SelectProcessDialog.py
jdProcessFileWatcher/gui/SettingsDialog.py
jdProcessFileWatcher/gui/WelcomeDialog.py
jdProcessFileWatcher/gui/__init__.py
jdProcessFileWatcher/translations/jdProcessFileWatcher_de.qm
jdProcessFileWatcher/translations/jdProcessFileWatcher_nl.qm
jdProcessFileWatcher/translations/jdProcessFileWatcher_ru.qm
jdProcessFileWatcher/ui_compiled/AboutDialog.py
jdProcessFileWatcher/ui_compiled/ActionsTable.py
jdProcessFileWatcher/ui_compiled/ExportDialog.py
jdProcessFileWatcher/ui_compiled/MainWindow.py
jdProcessFileWatcher/ui_compiled/PathActionsDialog.py
jdProcessFileWatcher/ui_compiled/RunCommandDialog.py
jdProcessFileWatcher/ui_compiled/RunProgramDialog.py
jdProcessFileWatcher/ui_compiled/SelectProcessDialog.py
jdProcessFileWatcher/ui_compiled/SettingsDialog.py
jdProcessFileWatcher/ui_compiled/WelcomeDialog.py
jdProcessFileWatcher/ui_compiled/__init__.py
jdProcessFileWatcher-2.0.dist-info/LICENSE
jdProcessFileWatcher-2.0.dist-info/METADATA
jdProcessFileWatcher-2.0.dist-info/WHEEL
jdProcessFileWatcher-2.0.dist-info/entry_points.txt
jdProcessFileWatcher-2.0.dist-info/top_level.txt
jdProcessFileWatcher-2.0.dist-info/RECORD
